compredict/__init__.py
compredict/client.py
compredict/connection.py
compredict/exceptions.py
compredict/singleton.py
compredict/resources/__init__.py
compredict/resources/base.py
compredict/resources/resources.py
compredict/utils/__init__.py
compredict/utils/authentications.py
compredict/utils/utils.py
examples/.env.example
examples/.gitignore
examples/__init__.py
examples/aws_callback_example.ipynb
examples/basic_ex.py
examples/multiple_callbacks_example.ipynb
tests/__init__.py
tests/conftest.py
tests/test_client.py
tests/test_connection.py
tests/test_utils.py
tests/media/example.json
tests/media/features.parquet
tests/media/parameters-example.json
tests/media/test.txt
COMPREDICT_AI_SDK-2.1.1.dist-info/METADATA
COMPREDICT_AI_SDK-2.1.1.dist-info/WHEEL
COMPREDICT_AI_SDK-2.1.1.dist-info/top_level.txt
COMPREDICT_AI_SDK-2.1.1.dist-info/RECORD
