Metadata-Version: 2.1
Name: COMPREDICT-AI-SDK
Version: 2.1.1
Summary: Connect Python applications with COMPREDICT AI Core.
Home-page: https://github.com/compredict/ai-sdk-python
Author: Ousama Esbel
Author-email: esbel@compredict.de
License: MIT
Keywords: COMPREDICT,AI,SDK,API,rest
Requires-Dist: requests (<3.0.0,>=2.20.1)
Requires-Dist: pandas (<2.0.0,>=1.0.0)
Provides-Extra: dev
Requires-Dist: flake8 (~=3.9.2) ; extra == 'dev'
Requires-Dist: pytest (~=6.2.4) ; extra == 'dev'
Requires-Dist: pytest-mock (~=3.6.1) ; extra == 'dev'
Requires-Dist: pytest-cov (~=2.12.1) ; extra == 'dev'
Requires-Dist: fastparquet (~=0.8.0) ; extra == 'dev'
